LICENSE
alist_proxy/__init__.py
alist_proxy/__main__.py
alist_proxy/py.typed
alist_proxy-0.1.3.2.dist-info/LICENSE
alist_proxy-0.1.3.2.dist-info/METADATA
alist_proxy-0.1.3.2.dist-info/WHEEL
alist_proxy-0.1.3.2.dist-info/entry_points.txt
alist_proxy-0.1.3.2.dist-info/RECORD
