Metadata-Version: 2.1
Name: alist_proxy
Version: 0.1.3.2
Summary: Python alist proxy and monitor.
Home-page: https://github.com/ChenyangGao/web-mount-packs/tree/main/python-alist-proxy
License: MIT
Keywords: alist,proxy,monitor
Author: ChenyangGao
Author-email: wosiwujm@gmail.com
Requires-Python: >=3.11,<4.0
Classifier: Development Status :: 4 - Beta
Classifier: Intended Audience :: Developers
Classifier: License :: OSI Approved :: MIT License
Classifier: Operating System :: OS Independent
Classifier: Programming Language :: Python
Classifier: Programming Language :: Python :: 3
Classifier: Programming Language :: Python :: 3.11
Classifier: Programming Language :: Python :: 3.12
Classifier: Programming Language :: Python :: 3.13
Classifier: Programming Language :: Python :: 3 :: Only
Classifier: Topic :: Software Development
Classifier: Topic :: Software Development :: Libraries
Classifier: Topic :: Software Development :: Libraries :: Python Modules
Requires-Dist: aiosqlite
Requires-Dist: blacksheep
Requires-Dist: bson
Requires-Dist: httpx
Requires-Dist: motor
Requires-Dist: orjson
Requires-Dist: p115qrcode (>=0.0.3)
Requires-Dist: python-alist (>=0.0.13.7)
Requires-Dist: python-cookietools (>=0.0.2)
Requires-Dist: python-dateutil
Requires-Dist: python-reverse-proxy (>=0.0.9.4)
Requires-Dist: redis
Requires-Dist: uvicorn
Requires-Dist: yarl
Project-URL: Repository, https://github.com/ChenyangGao/web-mount-packs/tree/main/python-alist-proxy
